CHANGES.txt
LICENSE.txt
MANIFEST.in
README.txt
setup.py
src/j01/__init__.py
src/j01.searcher.egg-info/PKG-INFO
src/j01.searcher.egg-info/SOURCES.txt
src/j01.searcher.egg-info/dependency_links.txt
src/j01.searcher.egg-info/namespace_packages.txt
src/j01.searcher.egg-info/not-zip-safe
src/j01.searcher.egg-info/requires.txt
src/j01.searcher.egg-info/top_level.txt
src/j01/searcher/__init__.py
src/j01/searcher/browser.zcml
src/j01/searcher/btn.py
src/j01/searcher/checker.txt
src/j01/searcher/configure.zcml
src/j01/searcher/criterion.pt
src/j01/searcher/criterion_with_connector.pt
src/j01/searcher/filter.pt
src/j01/searcher/filter_load.pt
src/j01/searcher/filter_save.pt
src/j01/searcher/interfaces.py
src/j01/searcher/jsform.py
src/j01/searcher/jswidget.py
src/j01/searcher/search.pt
src/j01/searcher/tests.py
src/j01/searcher/widget_input_connector.pt