Metadata-Version: 1.1
Name: j01.searcher
Version: 1.0.0
Summary: JSON-RPC layer for m01.searcher
Home-page: http://pypi.python.org/pypi/j01.searcher
Author: Roger Ineichen
Author-email: dev@projekt01.ch
License: ZPL 2.1
Keywords: zope3 z3c j01 searcher json-rpc
Platform: UNKNOWN
Classifier: Development Status :: 4 - Beta
Classifier: Environment :: Web Environment
Classifier: Intended Audience :: Developers
Classifier: License :: OSI Approved :: Zope Public License
Classifier: Programming Language :: Python
Classifier: Natural Language :: English
Classifier: Operating System :: OS Independent
Classifier: Topic :: Internet :: WWW/HTTP
Classifier: Framework :: Zope3
